rerum/__init__.py
rerum/cli.py
rerum/engine.py
rerum/rewriter.py
rerum/tests/__init__.py
rerum/tests/test_bidirectional.py
rerum/tests/test_bindings.py
rerum/tests/test_cli.py
rerum/tests/test_engine_methods.py
rerum/tests/test_equivalents.py
rerum/tests/test_expr_builder.py
rerum/tests/test_groups.py
rerum/tests/test_guards.py
rerum/tests/test_includes.py
rerum/tests/test_optimization.py
rerum/tests/test_priorities.py
rerum/tests/test_prove_equal.py
rerum/tests/test_rewriter.py
rerum/tests/test_sequencing.py
rerum/tests/test_strategies.py
rerum/tests/test_trace.py
rerum-0.4.0.dist-info/METADATA
rerum-0.4.0.dist-info/WHEEL
rerum-0.4.0.dist-info/entry_points.txt
rerum-0.4.0.dist-info/RECORD
