Metadata-Version: 2.4
Name: rerum
Version: 0.4.0
Summary: RERUM - Rewriting Expressions via Rules Using Morphisms
Project-URL: Homepage, https://github.com/queelius/rerum
Project-URL: Documentation, https://queelius.github.io/rerum
Project-URL: Repository, https://github.com/queelius/rerum
Project-URL: Issues, https://github.com/queelius/rerum/issues
Project-URL: Changelog, https://github.com/queelius/rerum/releases
Author: spinoza
License-Expression: MIT
Keywords: dsl,pattern-matching,rewriting,s-expressions,symbolic,symbolic-computation,term-rewriting
Classifier: Development Status :: 4 - Beta
Classifier: Intended Audience :: Developers
Classifier: Intended Audience :: Science/Research
Classifier: License :: OSI Approved :: MIT License
Classifier: Operating System :: OS Independent
Classifier: Programming Language :: Python :: 3
Classifier: Programming Language :: Python :: 3.9
Classifier: Programming Language :: Python :: 3.10
Classifier: Programming Language :: Python :: 3.11
Classifier: Programming Language :: Python :: 3.12
Classifier: Programming Language :: Python :: 3.13
Classifier: Topic :: Scientific/Engineering :: Mathematics
Classifier: Topic :: Software Development :: Libraries :: Python Modules
Classifier: Typing :: Typed
Requires-Python: >=3.9
Provides-Extra: dev
Requires-Dist: pytest-cov>=4.0; extra == 'dev'
Requires-Dist: pytest>=7.0; extra == 'dev'
Provides-Extra: docs
Requires-Dist: mkdocs-material>=9.0; extra == 'docs'
Requires-Dist: mkdocs>=1.5; extra == 'docs'
